{
  "meta": {
    "source": "AlanChand USD | TGJU & CoinDesk for others",
    "endpoints": {
      "usd": "https://alanchand.com/currencies-price/usd",
      "eur": "https://www.tgju.org/profile/price_eur",
      "gold18": "https://www.tgju.org/profile/tgju_gold_irg18",
      "ounce_usd_from_xaut": "https://www.coindesk.com/price/xaut",
      "btc_usd": "https://www.coindesk.com/price/bitcoin",
      "eth_usd": "https://www.coindesk.com/price/ethereum",
      "ton_usd": "https://www.coindesk.com/price/toncoin"
    },
    "updated_at": "2026-07-02T11:06:44.998Z",
    "updated_at_tehran": "2026-07-02T14:36:44+03:30"
  },
  "usd": {
    "label": "USD Free Market (Toman)",
    "value_toman_text": "۱۷۵,۴۰۰",
    "value_toman_number": 175400,
    "updated_at_text": "۱۴:۳۵ پنجشنبه ۱۱ تیر ۱۴۰۵",
    "updated_at_en": null,
    "ok": true,
    "error": null
  },
  "eur": {
    "raw": "2,001,500",
    "value_irr": 2001500,
    "value_toman": 200150,
    "ok": true,
    "error": null
  },
  "gold18": {
    "raw": "197,691,000",
    "value_irr": 197691000,
    "value_toman": 19769100,
    "ok": true,
    "error": null
  },
  "ons": {
    "label": "Gold Ounce (USD from XAUT)",
    "raw": "$4,049.98",
    "value_usd": 4049.98,
    "ok": true,
    "error": null
  },
  "btc": {
    "label": "Bitcoin (USD)",
    "raw": "$61,194.00",
    "value_usd": 61194,
    "ok": true,
    "error": null
  },
  "eth": {
    "label": "Ethereum (USD)",
    "raw": "$1,642.97",
    "value_usd": 1642.97,
    "ok": true,
    "error": null
  },
  "ton": {
    "label": "Toncoin (USD)",
    "raw": null,
    "value_usd": null,
    "ok": false,
    "error": "TON: parse USD failed"
  }
}