{
  "meta": {
    "source": "AlanChand USD | TGJU & CoinDesk for others",
    "endpoints": {
      "usd": "https://alanchand.com/currencies-price/usd",
      "eur": "https://www.tgju.org/profile/price_eur",
      "gold18": "https://www.tgju.org/profile/tgju_gold_irg18",
      "ounce_usd_from_xaut": "https://www.coindesk.com/price/xaut",
      "btc_usd": "https://www.coindesk.com/price/bitcoin",
      "eth_usd": "https://www.coindesk.com/price/ethereum",
      "ton_usd": "https://www.coindesk.com/price/toncoin"
    },
    "updated_at": "2025-10-02T17:41:36.802Z",
    "updated_at_tehran": "2025-10-02T21:11:36+03:30"
  },
  "usd": {
    "label": "USD Free Market (Toman)",
    "value_toman_text": "۱۱۷,۱۰۰",
    "value_toman_number": 117100,
    "updated_at_text": "ساعت: ۲۱:۱۰ (به وقت تهران)",
    "updated_at_en": "21:10",
    "ok": true,
    "error": null
  },
  "eur": {
    "raw": "1,384,100",
    "value_irr": 1384100,
    "value_toman": 138410,
    "ok": true,
    "error": null
  },
  "gold18": {
    "raw": "109,250,000",
    "value_irr": 109250000,
    "value_toman": 10925000,
    "ok": true,
    "error": null
  },
  "ons": {
    "label": "Gold Ounce (USD from XAUT)",
    "raw": "$3,850.00",
    "value_usd": 3850,
    "ok": true,
    "error": null
  },
  "btc": {
    "label": "Bitcoin (USD)",
    "raw": "$119,558.87",
    "value_usd": 119558.87,
    "ok": true,
    "error": null
  },
  "eth": {
    "label": "Ethereum (USD)",
    "raw": "$4,466.94",
    "value_usd": 4466.94,
    "ok": true,
    "error": null
  },
  "ton": {
    "label": "Toncoin (USD)",
    "raw": "$2.8206",
    "value_usd": 2.8206,
    "ok": true,
    "error": null
  }
}