{
  "meta": {
    "source": "AlanChand USD | TGJU & CoinDesk for others",
    "endpoints": {
      "usd": "https://alanchand.com/currencies-price/usd",
      "eur": "https://www.tgju.org/profile/price_eur",
      "gold18": "https://www.tgju.org/profile/tgju_gold_irg18",
      "ounce_usd_from_xaut": "https://www.coindesk.com/price/xaut",
      "btc_usd": "https://www.coindesk.com/price/bitcoin",
      "eth_usd": "https://www.coindesk.com/price/ethereum",
      "ton_usd": "https://www.coindesk.com/price/toncoin"
    },
    "updated_at": "2025-10-27T12:17:25.198Z",
    "updated_at_tehran": "2025-10-27T15:47:25+03:30"
  },
  "usd": {
    "label": "USD Free Market (Toman)",
    "value_toman_text": "۱۰۷,۷۵۰",
    "value_toman_number": 107750,
    "updated_at_text": "ساعت: ۱۵:۴۵ (به وقت تهران)",
    "updated_at_en": "15:45",
    "ok": true,
    "error": null
  },
  "eur": {
    "raw": "1,256,700",
    "value_irr": 1256700,
    "value_toman": 125670,
    "ok": true,
    "error": null
  },
  "gold18": {
    "raw": "106,480,000",
    "value_irr": 106480000,
    "value_toman": 10648000,
    "ok": true,
    "error": null
  },
  "ons": {
    "label": "Gold Ounce (USD from XAUT)",
    "raw": "$4,027.00",
    "value_usd": 4027,
    "ok": true,
    "error": null
  },
  "btc": {
    "label": "Bitcoin (USD)",
    "raw": "$115,258.17",
    "value_usd": 115258.17,
    "ok": true,
    "error": null
  },
  "eth": {
    "label": "Ethereum (USD)",
    "raw": "$4,157.20",
    "value_usd": 4157.2,
    "ok": true,
    "error": null
  },
  "ton": {
    "label": "Toncoin (USD)",
    "raw": "$2.2193",
    "value_usd": 2.2193,
    "ok": true,
    "error": null
  }
}