{
  "meta": {
    "source": "AlanChand USD | TGJU & CoinDesk for others",
    "endpoints": {
      "usd": "https://alanchand.com/currencies-price/usd",
      "eur": "https://www.tgju.org/profile/price_eur",
      "gold18": "https://www.tgju.org/profile/tgju_gold_irg18",
      "ounce_usd_from_xaut": "https://www.coindesk.com/price/xaut",
      "btc_usd": "https://www.coindesk.com/price/bitcoin",
      "eth_usd": "https://www.coindesk.com/price/ethereum",
      "ton_usd": "https://www.coindesk.com/price/toncoin"
    },
    "updated_at": "2026-07-21T12:48:16.759Z",
    "updated_at_tehran": "2026-07-21T16:18:16+03:30"
  },
  "usd": {
    "label": "USD Free Market (Toman)",
    "value_toman_text": "۱۹۱,۰۵۰",
    "value_toman_number": 191050,
    "updated_at_text": "۱۶:۱۵ سه‌شنبه ۳۰ تیر ۱۴۰۵",
    "updated_at_en": null,
    "ok": true,
    "error": null
  },
  "eur": {
    "raw": "2,170,900",
    "value_irr": 2170900,
    "value_toman": 217090,
    "ok": true,
    "error": null
  },
  "gold18": {
    "raw": "197,621,000",
    "value_irr": 197621000,
    "value_toman": 19762100,
    "ok": true,
    "error": null
  },
  "ons": {
    "label": "Gold Ounce (USD from XAUT)",
    "raw": "$4,050.08",
    "value_usd": 4050.08,
    "ok": true,
    "error": null
  },
  "btc": {
    "label": "Bitcoin (USD)",
    "raw": "$66,453.34",
    "value_usd": 66453.34,
    "ok": true,
    "error": null
  },
  "eth": {
    "label": "Ethereum (USD)",
    "raw": "$1,939.27",
    "value_usd": 1939.27,
    "ok": true,
    "error": null
  },
  "ton": {
    "label": "Toncoin (USD)",
    "raw": null,
    "value_usd": null,
    "ok": false,
    "error": "TON: parse USD failed"
  }
}