{
  "meta": {
    "source": "AlanChand USD | TGJU & CoinDesk for others",
    "endpoints": {
      "usd": "https://alanchand.com/currencies-price/usd",
      "eur": "https://www.tgju.org/profile/price_eur",
      "gold18": "https://www.tgju.org/profile/tgju_gold_irg18",
      "ounce_usd_from_xaut": "https://www.coindesk.com/price/xaut",
      "btc_usd": "https://www.coindesk.com/price/bitcoin",
      "eth_usd": "https://www.coindesk.com/price/ethereum",
      "ton_usd": "https://www.coindesk.com/price/toncoin"
    },
    "updated_at": "2025-10-25T19:26:21.921Z",
    "updated_at_tehran": "2025-10-25T22:56:21+03:30"
  },
  "usd": {
    "label": "USD Free Market (Toman)",
    "value_toman_text": "۱۰۶,۹۰۰",
    "value_toman_number": 106900,
    "updated_at_text": "ساعت: ۲۲:۵۵ (به وقت تهران)",
    "updated_at_en": "22:55",
    "ok": true,
    "error": null
  },
  "eur": {
    "raw": "1,244,100",
    "value_irr": 1244100,
    "value_toman": 124410,
    "ok": true,
    "error": null
  },
  "gold18": {
    "raw": "107,040,000",
    "value_irr": 107040000,
    "value_toman": 10704000,
    "ok": true,
    "error": null
  },
  "ons": {
    "label": "Gold Ounce (USD from XAUT)",
    "raw": "$4,111.29",
    "value_usd": 4111.29,
    "ok": true,
    "error": null
  },
  "btc": {
    "label": "Bitcoin (USD)",
    "raw": "$111,685.57",
    "value_usd": 111685.57,
    "ok": true,
    "error": null
  },
  "eth": {
    "label": "Ethereum (USD)",
    "raw": "$3,955.47",
    "value_usd": 3955.47,
    "ok": true,
    "error": null
  },
  "ton": {
    "label": "Toncoin (USD)",
    "raw": "$2.1626",
    "value_usd": 2.1626,
    "ok": true,
    "error": null
  }
}