{
  "meta": {
    "source": "AlanChand USD | TGJU & CoinDesk for others",
    "endpoints": {
      "usd": "https://alanchand.com/currencies-price/usd",
      "eur": "https://www.tgju.org/profile/price_eur",
      "gold18": "https://www.tgju.org/profile/tgju_gold_irg18",
      "ounce_usd_from_xaut": "https://www.coindesk.com/price/xaut",
      "btc_usd": "https://www.coindesk.com/price/bitcoin",
      "eth_usd": "https://www.coindesk.com/price/ethereum",
      "ton_usd": "https://www.coindesk.com/price/toncoin"
    },
    "updated_at": "2025-11-13T09:51:43.220Z",
    "updated_at_tehran": "2025-11-13T13:21:43+03:30"
  },
  "usd": {
    "label": "USD Free Market (Toman)",
    "value_toman_text": "۱۱۳,۱۰۰",
    "value_toman_number": 113100,
    "updated_at_text": "ساعت: ۱۳:۲۰ (به وقت تهران)",
    "updated_at_en": "13:20",
    "ok": true,
    "error": null
  },
  "eur": {
    "raw": "1,319,300",
    "value_irr": 1319300,
    "value_toman": 131930,
    "ok": true,
    "error": null
  },
  "gold18": {
    "raw": "117,110,000",
    "value_irr": 117110000,
    "value_toman": 11711000,
    "ok": true,
    "error": null
  },
  "ons": {
    "label": "Gold Ounce (USD from XAUT)",
    "raw": "$4,217.53",
    "value_usd": 4217.53,
    "ok": true,
    "error": null
  },
  "btc": {
    "label": "Bitcoin (USD)",
    "raw": "$102,858.55",
    "value_usd": 102858.55,
    "ok": true,
    "error": null
  },
  "eth": {
    "label": "Ethereum (USD)",
    "raw": null,
    "value_usd": null,
    "ok": false,
    "error": "ETH: parse USD failed"
  },
  "ton": {
    "label": "Toncoin (USD)",
    "raw": "$2.0497",
    "value_usd": 2.0497,
    "ok": true,
    "error": null
  }
}