{
  "meta": {
    "source": "AlanChand USD | TGJU & CoinDesk for others",
    "endpoints": {
      "usd": "https://alanchand.com/currencies-price/usd",
      "eur": "https://www.tgju.org/profile/price_eur",
      "gold18": "https://www.tgju.org/profile/tgju_gold_irg18",
      "ounce_usd_from_xaut": "https://www.coindesk.com/price/xaut",
      "btc_usd": "https://www.coindesk.com/price/bitcoin",
      "eth_usd": "https://www.coindesk.com/price/ethereum",
      "ton_usd": "https://www.coindesk.com/price/toncoin"
    },
    "updated_at": "2026-01-28T20:17:50.906Z",
    "updated_at_tehran": "2026-01-28T23:47:50+03:30"
  },
  "usd": {
    "label": "USD Free Market (Toman)",
    "value_toman_text": "۱۶۱,۲۰۰",
    "value_toman_number": 161200,
    "updated_at_text": "ساعت: ۲۳:۴۵ (به وقت تهران)",
    "updated_at_en": "23:45",
    "ok": true,
    "error": null
  },
  "eur": {
    "raw": "1,904,400",
    "value_irr": 1904400,
    "value_toman": 190440,
    "ok": true,
    "error": null
  },
  "gold18": {
    "raw": "157,701,000",
    "value_irr": 157701000,
    "value_toman": 15770100,
    "ok": true,
    "error": null
  },
  "ons": {
    "label": "Gold Ounce (USD from XAUT)",
    "raw": "$5,332.88",
    "value_usd": 5332.88,
    "ok": true,
    "error": null
  },
  "btc": {
    "label": "Bitcoin (USD)",
    "raw": "$89,506.32",
    "value_usd": 89506.32,
    "ok": true,
    "error": null
  },
  "eth": {
    "label": "Ethereum (USD)",
    "raw": "$3,017.61",
    "value_usd": 3017.61,
    "ok": true,
    "error": null
  },
  "ton": {
    "label": "Toncoin (USD)",
    "raw": "$1.5269",
    "value_usd": 1.5269,
    "ok": true,
    "error": null
  }
}