{
  "meta": {
    "source": "AlanChand USD | TGJU & CoinDesk for others",
    "endpoints": {
      "usd": "https://alanchand.com/currencies-price/usd",
      "eur": "https://www.tgju.org/profile/price_eur",
      "gold18": "https://www.tgju.org/profile/tgju_gold_irg18",
      "ounce_usd_from_xaut": "https://www.coindesk.com/price/xaut",
      "btc_usd": "https://www.coindesk.com/price/bitcoin",
      "eth_usd": "https://www.coindesk.com/price/ethereum",
      "ton_usd": "https://www.coindesk.com/price/toncoin"
    },
    "updated_at": "2025-12-17T11:48:13.474Z",
    "updated_at_tehran": "2025-12-17T15:18:13+03:30"
  },
  "usd": {
    "label": "USD Free Market (Toman)",
    "value_toman_text": "۱۳۱,۶۰۰",
    "value_toman_number": 131600,
    "updated_at_text": "ساعت: ۱۵:۱۵ (به وقت تهران)",
    "updated_at_en": "15:15",
    "ok": true,
    "error": null
  },
  "eur": {
    "raw": "1,542,600",
    "value_irr": 1542600,
    "value_toman": 154260,
    "ok": true,
    "error": null
  },
  "gold18": {
    "raw": "137,962,000",
    "value_irr": 137962000,
    "value_toman": 13796200,
    "ok": true,
    "error": null
  },
  "ons": {
    "label": "Gold Ounce (USD from XAUT)",
    "raw": "$4,335.56",
    "value_usd": 4335.56,
    "ok": true,
    "error": null
  },
  "btc": {
    "label": "Bitcoin (USD)",
    "raw": "$86,893.10",
    "value_usd": 86893.1,
    "ok": true,
    "error": null
  },
  "eth": {
    "label": "Ethereum (USD)",
    "raw": "$2,929.85",
    "value_usd": 2929.85,
    "ok": true,
    "error": null
  },
  "ton": {
    "label": "Toncoin (USD)",
    "raw": "$1.5077",
    "value_usd": 1.5077,
    "ok": true,
    "error": null
  }
}