{
  "meta": {
    "source": "AlanChand USD | TGJU & CoinDesk for others",
    "endpoints": {
      "usd": "https://alanchand.com/currencies-price/usd",
      "eur": "https://www.tgju.org/profile/price_eur",
      "gold18": "https://www.tgju.org/profile/tgju_gold_irg18",
      "ounce_usd_from_xaut": "https://www.coindesk.com/price/xaut",
      "btc_usd": "https://www.coindesk.com/price/bitcoin",
      "eth_usd": "https://www.coindesk.com/price/ethereum",
      "ton_usd": "https://www.coindesk.com/price/toncoin"
    },
    "updated_at": "2026-01-05T17:29:11.367Z",
    "updated_at_tehran": "2026-01-05T20:59:11+03:30"
  },
  "usd": {
    "label": "USD Free Market (Toman)",
    "value_toman_text": "۱۴۳,۸۰۰",
    "value_toman_number": 143800,
    "updated_at_text": "ساعت: ۲۰:۵۵ (به وقت تهران)",
    "updated_at_en": "20:55",
    "ok": true,
    "error": null
  },
  "eur": {
    "raw": "1,673,900",
    "value_irr": 1673900,
    "value_toman": 167390,
    "ok": true,
    "error": null
  },
  "gold18": {
    "raw": "156,645,000",
    "value_irr": 156645000,
    "value_toman": 15664500,
    "ok": true,
    "error": null
  },
  "ons": {
    "label": "Gold Ounce (USD from XAUT)",
    "raw": "$4,439.35",
    "value_usd": 4439.35,
    "ok": true,
    "error": null
  },
  "btc": {
    "label": "Bitcoin (USD)",
    "raw": "$93,324.51",
    "value_usd": 93324.51,
    "ok": true,
    "error": null
  },
  "eth": {
    "label": "Ethereum (USD)",
    "raw": "$3,162.17",
    "value_usd": 3162.17,
    "ok": true,
    "error": null
  },
  "ton": {
    "label": "Toncoin (USD)",
    "raw": "$1.8855",
    "value_usd": 1.8855,
    "ok": true,
    "error": null
  }
}