{
  "meta": {
    "source": "AlanChand USD | TGJU & CoinDesk for others",
    "endpoints": {
      "usd": "https://alanchand.com/currencies-price/usd",
      "eur": "https://www.tgju.org/profile/price_eur",
      "gold18": "https://www.tgju.org/profile/tgju_gold_irg18",
      "ounce_usd_from_xaut": "https://www.coindesk.com/price/xaut",
      "btc_usd": "https://www.coindesk.com/price/bitcoin",
      "eth_usd": "https://www.coindesk.com/price/ethereum",
      "ton_usd": "https://www.coindesk.com/price/toncoin"
    },
    "updated_at": "2025-11-08T21:39:53.353Z",
    "updated_at_tehran": "2025-11-09T01:09:53+03:30"
  },
  "usd": {
    "label": "USD Free Market (Toman)",
    "value_toman_text": null,
    "value_toman_number": null,
    "updated_at_text": null,
    "updated_at_en": null,
    "ok": false,
    "error": "HTTP 526 fetching https://alanchand.com/currencies-price/usd"
  },
  "eur": {
    "raw": "1,246,800",
    "value_irr": 1246800,
    "value_toman": 124680,
    "ok": true,
    "error": null
  },
  "gold18": {
    "raw": "104,490,000",
    "value_irr": 104490000,
    "value_toman": 10449000,
    "ok": true,
    "error": null
  },
  "ons": {
    "label": "Gold Ounce (USD from XAUT)",
    "raw": "$3,984.52",
    "value_usd": 3984.52,
    "ok": true,
    "error": null
  },
  "btc": {
    "label": "Bitcoin (USD)",
    "raw": "$102,296.69",
    "value_usd": 102296.69,
    "ok": true,
    "error": null
  },
  "eth": {
    "label": "Ethereum (USD)",
    "raw": "$3,406.11",
    "value_usd": 3406.11,
    "ok": true,
    "error": null
  },
  "ton": {
    "label": "Toncoin (USD)",
    "raw": "$2.0926",
    "value_usd": 2.0926,
    "ok": true,
    "error": null
  }
}