{
  "meta": {
    "source": "AlanChand USD | TGJU & CoinDesk for others",
    "endpoints": {
      "usd": "https://alanchand.com/currencies-price/usd",
      "eur": "https://www.tgju.org/profile/price_eur",
      "gold18": "https://www.tgju.org/profile/tgju_gold_irg18",
      "ounce_usd_from_xaut": "https://www.coindesk.com/price/xaut",
      "btc_usd": "https://www.coindesk.com/price/bitcoin",
      "eth_usd": "https://www.coindesk.com/price/ethereum",
      "ton_usd": "https://www.coindesk.com/price/toncoin"
    },
    "updated_at": "2025-12-06T11:23:33.509Z",
    "updated_at_tehran": "2025-12-06T14:53:33+03:30"
  },
  "usd": {
    "label": "USD Free Market (Toman)",
    "value_toman_text": "۱۲۱,۵۵۰",
    "value_toman_number": 121550,
    "updated_at_text": "ساعت: ۱۴:۵۰ (به وقت تهران)",
    "updated_at_en": "14:50",
    "ok": true,
    "error": null
  },
  "eur": {
    "raw": "1,417,200",
    "value_irr": 1417200,
    "value_toman": 141720,
    "ok": true,
    "error": null
  },
  "gold18": {
    "raw": "124,860,000",
    "value_irr": 124860000,
    "value_toman": 12486000,
    "ok": true,
    "error": null
  },
  "ons": {
    "label": "Gold Ounce (USD from XAUT)",
    "raw": "$4,204.14",
    "value_usd": 4204.14,
    "ok": true,
    "error": null
  },
  "btc": {
    "label": "Bitcoin (USD)",
    "raw": "$89,593.42",
    "value_usd": 89593.42,
    "ok": true,
    "error": null
  },
  "eth": {
    "label": "Ethereum (USD)",
    "raw": "$3,037.78",
    "value_usd": 3037.78,
    "ok": true,
    "error": null
  },
  "ton": {
    "label": "Toncoin (USD)",
    "raw": "$1.5723",
    "value_usd": 1.5723,
    "ok": true,
    "error": null
  }
}