{
  "meta": {
    "source": "AlanChand USD | TGJU & CoinDesk for others",
    "endpoints": {
      "usd": "https://alanchand.com/currencies-price/usd",
      "eur": "https://www.tgju.org/profile/price_eur",
      "gold18": "https://www.tgju.org/profile/tgju_gold_irg18",
      "ounce_usd_from_xaut": "https://www.coindesk.com/price/xaut",
      "btc_usd": "https://www.coindesk.com/price/bitcoin",
      "eth_usd": "https://www.coindesk.com/price/ethereum",
      "ton_usd": "https://www.coindesk.com/price/toncoin"
    },
    "updated_at": "2025-10-18T21:53:10.240Z",
    "updated_at_tehran": "2025-10-19T01:23:10+03:30"
  },
  "usd": {
    "label": "USD Free Market (Toman)",
    "value_toman_text": "۱۰۷,۳۰۰",
    "value_toman_number": 107300,
    "updated_at_text": "ساعت: ۰۱:۲۰ (به وقت تهران)",
    "updated_at_en": "01:20",
    "ok": true,
    "error": null
  },
  "eur": {
    "raw": "1,241,100",
    "value_irr": 1241100,
    "value_toman": 124110,
    "ok": true,
    "error": null
  },
  "gold18": {
    "raw": "109,090,000",
    "value_irr": 109090000,
    "value_toman": 10909000,
    "ok": true,
    "error": null
  },
  "ons": {
    "label": "Gold Ounce (USD from XAUT)",
    "raw": "$4,231.59",
    "value_usd": 4231.59,
    "ok": true,
    "error": null
  },
  "btc": {
    "label": "Bitcoin (USD)",
    "raw": "$107,180.09",
    "value_usd": 107180.09,
    "ok": true,
    "error": null
  },
  "eth": {
    "label": "Ethereum (USD)",
    "raw": "$3,890.92",
    "value_usd": 3890.92,
    "ok": true,
    "error": null
  },
  "ton": {
    "label": "Toncoin (USD)",
    "raw": "$2.1558",
    "value_usd": 2.1558,
    "ok": true,
    "error": null
  }
}