{
  "meta": {
    "source": "AlanChand USD | TGJU & CoinDesk for others",
    "endpoints": {
      "usd": "https://alanchand.com/currencies-price/usd",
      "eur": "https://www.tgju.org/profile/price_eur",
      "gold18": "https://www.tgju.org/profile/tgju_gold_irg18",
      "ounce_usd_from_xaut": "https://www.coindesk.com/price/xaut",
      "btc_usd": "https://www.coindesk.com/price/bitcoin",
      "eth_usd": "https://www.coindesk.com/price/ethereum",
      "ton_usd": "https://www.coindesk.com/price/toncoin"
    },
    "updated_at": "2025-10-24T13:53:11.133Z",
    "updated_at_tehran": "2025-10-24T17:23:11+03:30"
  },
  "usd": {
    "label": "USD Free Market (Toman)",
    "value_toman_text": "۱۰۸,۵۵۰",
    "value_toman_number": 108550,
    "updated_at_text": "ساعت: ۱۷:۲۰ (به وقت تهران)",
    "updated_at_en": "17:20",
    "ok": true,
    "error": null
  },
  "eur": {
    "raw": "1,259,000",
    "value_irr": 1259000,
    "value_toman": 125900,
    "ok": true,
    "error": null
  },
  "gold18": {
    "raw": "108,090,000",
    "value_irr": 108090000,
    "value_toman": 10809000,
    "ok": true,
    "error": null
  },
  "ons": {
    "label": "Gold Ounce (USD from XAUT)",
    "raw": "$4,116.88",
    "value_usd": 4116.88,
    "ok": true,
    "error": null
  },
  "btc": {
    "label": "Bitcoin (USD)",
    "raw": "$110,604.60",
    "value_usd": 110604.6,
    "ok": true,
    "error": null
  },
  "eth": {
    "label": "Ethereum (USD)",
    "raw": "$3,932.09",
    "value_usd": 3932.09,
    "ok": true,
    "error": null
  },
  "ton": {
    "label": "Toncoin (USD)",
    "raw": "$2.1622",
    "value_usd": 2.1622,
    "ok": true,
    "error": null
  }
}