{
  "meta": {
    "source": "AlanChand USD | TGJU & CoinDesk for others",
    "endpoints": {
      "usd": "https://alanchand.com/currencies-price/usd",
      "eur": "https://www.tgju.org/profile/price_eur",
      "gold18": "https://www.tgju.org/profile/tgju_gold_irg18",
      "ounce_usd_from_xaut": "https://www.coindesk.com/price/xaut",
      "btc_usd": "https://www.coindesk.com/price/bitcoin",
      "eth_usd": "https://www.coindesk.com/price/ethereum",
      "ton_usd": "https://www.coindesk.com/price/toncoin"
    },
    "updated_at": "2026-02-04T21:42:31.650Z",
    "updated_at_tehran": "2026-02-05T01:12:31+03:30"
  },
  "usd": {
    "label": "USD Free Market (Toman)",
    "value_toman_text": "۱۵۷,۵۰۰",
    "value_toman_number": 157500,
    "updated_at_text": "ساعت: ۰۱:۱۰ (به وقت تهران)",
    "updated_at_en": "01:10",
    "ok": true,
    "error": null
  },
  "eur": {
    "raw": null,
    "value_irr": null,
    "value_toman": null,
    "ok": false,
    "error": "HTTP 404 fetching https://www.tgju.org/profile/price_eur"
  },
  "gold18": {
    "raw": "197,621,000",
    "value_irr": 197621000,
    "value_toman": 19762100,
    "ok": true,
    "error": null
  },
  "ons": {
    "label": "Gold Ounce (USD from XAUT)",
    "raw": null,
    "value_usd": null,
    "ok": false,
    "error": "HTTP 429 fetching https://www.coindesk.com/price/xaut"
  },
  "btc": {
    "label": "Bitcoin (USD)",
    "raw": null,
    "value_usd": null,
    "ok": false,
    "error": "HTTP 429 fetching https://www.coindesk.com/price/bitcoin"
  },
  "eth": {
    "label": "Ethereum (USD)",
    "raw": null,
    "value_usd": null,
    "ok": false,
    "error": "HTTP 429 fetching https://www.coindesk.com/price/ethereum"
  },
  "ton": {
    "label": "Toncoin (USD)",
    "raw": null,
    "value_usd": null,
    "ok": false,
    "error": "HTTP 429 fetching https://www.coindesk.com/price/toncoin"
  }
}